SoftDB/__init__.py
SoftDB/test.py
SoftDB/parts/hash_tool/__init__.py
SoftDB/parts/hash_tool/test.py
SoftDB/parts/python_layer/__init__.py
SoftDB/parts/python_layer/test.py
SoftDB/parts/sql_layer/__init__.py
SoftDB/parts/sql_layer/test.py
SoftDB-0.0.5.dist-info/METADATA
SoftDB-0.0.5.dist-info/WHEEL
SoftDB-0.0.5.dist-info/top_level.txt
SoftDB-0.0.5.dist-info/RECORD
