Metadata-Version: 2.1
Name: SoftDB
Version: 0.0.5
Summary: DB that can be manipulated as if they were objects in memory
Home-page: https://github.co.jp/
Author: le lattelle
Author-email: g.tiger.ml@gmail.com
License: MIT
Platform: UNKNOWN
Classifier: Programming Language :: Python :: 3
Classifier: Topic :: Software Development :: Libraries
Classifier: License :: OSI Approved :: MIT License
Requires-Dist: relpath
Requires-Dist: sout
Requires-Dist: tqdm
Requires-Dist: xxhash
